{
  "id": "marshall",
  "name": "MARSHALL ",
  "fullName": "escala de Marshall modificada ",
  "description": "Determinar la presencia y gravedad de FALLA ORGANICA en pancreatitis.",
  "category": "pancreas",
  "duration": "<1 min",
  "questions": [
        {
          "id": "resp_class",
          "text": "Sistema Respiratorio (PaO₂/FiO₂ en mmHg)",
          "options": [
            { "id": "eye1", "label": "0: > 400", "score": 0 },
            { "id": "eye2", "label": "1: 301-400", "score": 1 },
            { "id": "eye3", "label": "2: 201-300", "score": 10 },
            { "id": "eye4", "label": "3: 101-200", "score": 10 },
            { "id": "eye5", "label": "4: ≤ 101", "score": 10 }
          ]
        },
        {
          "id": "ren_class",
          "text": "Sistema Renal (Creatinina sérica en mg/dL)",
          "options": [
            { "id": "ver1", "label": "0: < 1.4", "score": 0 },
            { "id": "ver2", "label": "1: 1.4-1.8", "score": 1 },
            { "id": "ver3", "label": "2: 1.9-3.6", "score": 10 },
            { "id": "ver4", "label": "3: 3.6-4.9", "score": 10 },
            { "id": "ver5", "label": "4: > 4.9", "score": 10 }
          ]
        },
        {
          "id": "car_class",
          "text": "Sistema Cardiovascular (Presión Arterial Sistólica en mmHg)",
          "options": [
            { "id": "mot1", "label": "0: > 90", "score": 0 },
            { "id": "mot2", "label": "1: < 90 responde a volumen", "score": 1 },
            { "id": "mot3", "label": "2: < 90 No responde a volumen ", "score": 10 },
            { "id": "mot4", "label": "3: < 90 No responde a volumen y pH < 7.3", "score": 10 },
            { "id": "mot5", "label": "4: < 90 No responde a volumen y pH < 7.2", "score": 10 }
          ]
        }
      ],
      "interpretation": [
        { "min": 0, "max": 9, "label": "Pancreatitis Aguda Leve", "description": "No presenta insuficiencia de órganos ni complicaciones locales o sistémicas.", "severity": "low" },
        { "min": 10, "max": 100, "label": "Falla organica", "description": "Pancreatitis Moderadamente Grave: Falla organica transitoria (,48h) - Pancreatitis Grave: Falla organica persistente (>48h)", "severity": "critical" }
      ]
    }